samotpravil/__init__.py
samotpravil/client.py
samotpravil/exceptions.py
samotpravil-0.0.2.dist-info/METADATA
samotpravil-0.0.2.dist-info/WHEEL
samotpravil-0.0.2.dist-info/licenses/LICENSE
samotpravil-0.0.2.dist-info/RECORD
