Metadata-Version: 2.3
Name: samotpravil
Version: 0.0.2
Author-email: Samotpravil <support@samotpravil.ru>
License-File: LICENSE
Classifier: License :: OSI Approved :: MIT License
Classifier: Operating System :: OS Independent
Classifier: Programming Language :: Python :: 3
Requires-Python: >=3.10.0
